xgcondb/__init__.py
xugu_mcp/__init__.py
xugu_mcp/http_server.py
xugu_mcp/main.py
xugu_mcp/chat2sql/__init__.py
xugu_mcp/chat2sql/engine.py
xugu_mcp/chat2sql/prompt_builder.py
xugu_mcp/chat2sql/schema_manager.py
xugu_mcp/chat2sql/sql_sanitizer.py
xugu_mcp/chat2sql/sql_validator.py
xugu_mcp/config/__init__.py
xugu_mcp/config/defaults.py
xugu_mcp/config/settings.py
xugu_mcp/db/__init__.py
xugu_mcp/db/connection.py
xugu_mcp/db/operations.py
xugu_mcp/llm/__init__.py
xugu_mcp/llm/base.py
xugu_mcp/llm/claude.py
xugu_mcp/llm/factory.py
xugu_mcp/llm/local.py
xugu_mcp/llm/openai.py
xugu_mcp/llm/zhipu.py
xugu_mcp/mcp_resources/__init__.py
xugu_mcp/mcp_resources/schema_resources.py
xugu_mcp/mcp_tools/__init__.py
xugu_mcp/mcp_tools/admin_tools.py
xugu_mcp/mcp_tools/audit_tools.py
xugu_mcp/mcp_tools/chat2sql_lightweight_tools.py
xugu_mcp/mcp_tools/chat2sql_tools.py
xugu_mcp/mcp_tools/ddl_tools.py
xugu_mcp/mcp_tools/dml_tools.py
xugu_mcp/mcp_tools/schema_tools.py
xugu_mcp/security/__init__.py
xugu_mcp/security/access_control.py
xugu_mcp/security/audit.py
xugu_mcp/security/hooks.py
xugu_mcp/security/rate_limiter.py
xugu_mcp/utils/__init__.py
xugu_mcp/utils/errors.py
xugu_mcp/utils/helpers.py
xugu_mcp/utils/logging.py
xugu_mcp-0.1.0.data/data/xgcondb-linux-64/__init__.py
xugu_mcp-0.1.0.data/data/xgcondb-linux-64/_pyxgdb.cpython-310-x86_64-linux-gnu.so
xugu_mcp-0.1.0.data/data/xgcondb-linux-64/_pyxgdb.cpython-311-x86_64-linux-gnu.so
xugu_mcp-0.1.0.data/data/xgcondb-linux-64/_pyxgdb.cpython-34m.so
xugu_mcp-0.1.0.data/data/xgcondb-linux-64/_pyxgdb.cpython-36m-x86_64-linux-gnu.so
xugu_mcp-0.1.0.data/data/xgcondb-linux-64/_pyxgdb.cpython-37m-x86_64-linux-gnu.so
xugu_mcp-0.1.0.data/data/xgcondb-linux-64/_pyxgdb.cpython-38-x86_64-linux-gnu.so
xugu_mcp-0.1.0.data/data/xgcondb-linux-64/_pyxgdb.cpython-39-x86_64-linux-gnu.so
xugu_mcp-0.1.0.data/data/xgcondb-linux-64/_pyxgdb.so
xugu_mcp-0.1.0.data/data/xgcondb-linux-64/libxugusql.so
xugu_mcp-0.1.0.data/data/xgcondb-linux-arm64/__init__.py
xugu_mcp-0.1.0.dist-info/METADATA
xugu_mcp-0.1.0.dist-info/WHEEL
xugu_mcp-0.1.0.dist-info/entry_points.txt
xugu_mcp-0.1.0.dist-info/licenses/LICENSE
xugu_mcp-0.1.0.dist-info/RECORD
