Metadata-Version: 2.4
Name: xugu-mcp
Version: 0.1.0
Summary: XuguDB MCP Server with Chat2SQL support - A Model Context Protocol server for XuguDB (虚谷数据库) with full DDL/DML support, multi-LLM provider integration, and natural language to SQL conversion capabilities.
Project-URL: Homepage, https://github.com/xugudb/xugu-mcp
Project-URL: Documentation, https://github.com/xugudb/xugu-mcp#readme
Project-URL: Repository, https://github.com/xugudb/xugu-mcp
Project-URL: Issues, https://github.com/xugudb/xugu-mcp/issues
Project-URL: Changelog, https://github.com/xugudb/xugu-mcp/blob/main/CHANGELOG.md
Author-email: XuguDB Community <info@xugudb.com>
Maintainer-email: XuguDB Community <info@xugudb.com>
License: MIT
License-File: LICENSE
Keywords: anthropic,chat2sql,claude,database,database-driver,llm,mcp,model-context-protocol,openai,sql,sql-tools,xugu,xugudb,虚谷数据库
Classifier: Development Status :: 4 - Beta
Classifier: Intended Audience :: Developers
Classifier: License :: OSI Approved :: MIT License
Classifier: Operating System :: OS Independent
Classifier: Programming Language :: Python :: 3
Classifier: Programming Language :: Python :: 3.11
Classifier: Programming Language :: Python :: 3.12
Classifier: Topic :: Database
Classifier: Topic :: Software Development :: Libraries :: Python Modules
Classifier: Typing :: Typed
Requires-Python: >=3.11
Requires-Dist: aiofiles>=24.0.0
Requires-Dist: anthropic>=0.40.0
Requires-Dist: httpx>=0.27.0
Requires-Dist: loguru>=0.7.0
Requires-Dist: mcp[cli]>=1.25.0
Requires-Dist: openai>=1.0.0
Requires-Dist: psutil>=6.0.0
Requires-Dist: pydantic-settings>=2.0.0
Requires-Dist: pydantic>=2.0.0
Requires-Dist: python-dotenv>=1.0.0
Requires-Dist: pyyaml>=6.0.0
Requires-Dist: sqlparse>=0.5.0
Requires-Dist: uvicorn>=0.30.0
Provides-Extra: dev
Requires-Dist: black>=24.0.0; extra == 'dev'
Requires-Dist: mypy>=1.0.0; extra == 'dev'
Requires-Dist: pytest-asyncio>=0.24.0; extra == 'dev'
Requires-Dist: pytest-cov>=5.0.0; extra == 'dev'
Requires-Dist: pytest>=8.0.0; extra == 'dev'
Requires-Dist: ruff>=0.6.0; extra == 'dev'
